kicad_testpoints/.editorconfig
kicad_testpoints/.gitignore
kicad_testpoints/.travis.yml
kicad_testpoints/__init__.py
kicad_testpoints/cli.py
kicad_testpoints/file_io.py
kicad_testpoints/kicad_testpoints.py
kicad_testpoints/.github/ISSUE_TEMPLATE.md
kicad_testpoints-0.3.0.dist-info/LICENSE
kicad_testpoints-0.3.0.dist-info/METADATA
kicad_testpoints-0.3.0.dist-info/WHEEL
kicad_testpoints-0.3.0.dist-info/entry_points.txt
kicad_testpoints-0.3.0.dist-info/top_level.txt
kicad_testpoints-0.3.0.dist-info/RECORD
