Metadata-Version: 2.1
Name: kicad_testpoints
Version: 0.3.0
Summary: Extract pad positions from a kicad PCBNEW file with net data.
Author-email: Simon Hobbs <simon.hobbs@electrooptical.net>
License: GNU LESSER GENERAL PUBLIC LICENSE
Project-URL: github, https://github.com/snhobbs/kicad-testpoints.git
Keywords: kicad_testpoints,kicad,python,eda,electronics,pcb,manufacturing
Classifier: Development Status :: 2 - Pre-Alpha
Classifier: Intended Audience :: Developers
Classifier: Natural Language :: English
Classifier: Programming Language :: Python :: 3
Classifier: Programming Language :: Python :: 3.6
Classifier: Programming Language :: Python :: 3.7
Classifier: Programming Language :: Python :: 3.8
Classifier: Programming Language :: Python :: 3.9
Classifier: Programming Language :: Python :: 3.10
Classifier: Programming Language :: Python :: 3.11
Requires-Python: >=3.8
License-File: LICENSE
Requires-Dist: click >=7.0
Requires-Dist: pandas
Requires-Dist: numpy
